dock/__init__.py
dock/docker.py
dock/formula/__init__.py
dock/formula/docker-gc.py
dock/formula/mongodb.py
dock_upload_test-2.0.2.dist-info/DESCRIPTION.rst
dock_upload_test-2.0.2.dist-info/entry_points.txt
dock_upload_test-2.0.2.dist-info/METADATA
dock_upload_test-2.0.2.dist-info/metadata.json
dock_upload_test-2.0.2.dist-info/RECORD
dock_upload_test-2.0.2.dist-info/top_level.txt
dock_upload_test-2.0.2.dist-info/WHEEL
